{
  "title": "git push --force로 팀 작업을 날렸을 때 살린 방법",
  "date": "2025-09-19",
  "category": "git",
  "tags": [
    "tags: git",
    "reflog",
    "데이터복구",
    "실수복구"
  ],
  "description": "rebase 후 git push --force로 팀원들 작업까지 날려버린 절망적인 상황에서 git reflog로 모든 것을 복구한 실제 경험담입니다. 단계별 복구 과정과 예방법을 공유합니다.",
  "thumbnail": "thumbnail.jpg",
  "status": "ready-to-publish",
  "velog_url": "",
  "quality_score": 8.0,
  "workflow": {
    "created_date": "2025-09-19",
    "moved_to_archive": "2025-09-19 09:26:28",
    "ready_for_publish": true
  }
}
